{
  "chain_id": "staffordersmobile-260401-114201-9ed3",
  "template": "consensus-with-discussion-v2",
  "page": "StaffOrdersMobile",
  "total_steps": 5,
  "completed_step": 4,
  "status": "completed",
  "steps": {
    "1-cc-writer": {
      "task_id": "task-260401-114207-staffordersmobile-cc-writer",
      "step_name": "cc-writer",
      "chain_step": 1,
      "status": "completed",
      "cost": "0.78",
      "completed": "2026-04-01T11:52:35+05:00",
      "runner": "cc",
      "duration_sec": 281,
      "files_count": 0
    },
    "1-codex-writer": {
      "task_id": "task-260401-114207-staffordersmobile-codex-writer",
      "step_name": "codex-writer",
      "chain_step": 1,
      "status": "completed",
      "cost": "183k tok",
      "completed": "2026-04-01T11:52:36+05:00",
      "runner": "codex",
      "duration_sec": 612,
      "files_count": 0
    },
    "2-comparator": {
      "task_id": "task-260401-115337-staffordersmobile",
      "step_name": "comparator",
      "chain_step": 2,
      "status": "completed",
      "cost": "0.47",
      "completed": "2026-04-01T11:55:49+05:00",
      "runner": "cc",
      "duration_sec": 132,
      "files_count": 0
    },
    "3-discussion-cc-only": {
      "task_id": "task-260401-115649-staffordersmobile",
      "step_name": "discussion-cc-only",
      "chain_step": 3,
      "status": "completed",
      "cost": "0.47",
      "completed": "2026-04-01T11:58:16+05:00",
      "runner": "cc",
      "duration_sec": 87,
      "files_count": 0
    },
    "4-merge": {
      "task_id": "task-260401-115916-staffordersmobile",
      "step_name": "merge",
      "chain_step": 4,
      "status": "completed",
      "cost": "1.64",
      "completed": "2026-04-01T12:07:38+05:00",
      "runner": "cc",
      "duration_sec": 502,
      "files_count": 2
    }
  },
  "created": "2026-04-01T11:42:01+05:00",
  "inter_step_delay_sec": 60,
  "last_step_completed_at": "2026-04-01T12:07:38+05:00",
  "step_names": [
    "cc-writer",
    "codex-writer",
    "comparator",
    "discussion-cc-only",
    "merge"
  ],
  "tg_msg_id": "420",
  "completed": "2026-04-01T12:07:38+05:00"
}