{
  "chain_id": "testpage-260319-234320",
  "template": "consensus",
  "page": "TestPage",
  "total_steps": 4,
  "completed_step": 3,
  "status": "completed",
  "steps": {
    "1-codex-writer": {
      "task_id": "task-260319-234321-codex-writer",
      "step_name": "codex-writer",
      "chain_step": 1,
      "status": "completed",
      "cost": "0.00",
      "completed": "2026-03-19T23:49:00+05:00",
      "runner": "codex",
      "duration_sec": 338,
      "files_count": 0
    },
    "1-cc-writer": {
      "task_id": "task-260319-234321-cc-writer",
      "step_name": "cc-writer",
      "chain_step": 1,
      "status": "completed",
      "cost": "0.37",
      "completed": "2026-03-19T23:48:59+05:00",
      "runner": "cc",
      "duration_sec": 193,
      "files_count": 0
    },
    "2-comparator": {
      "task_id": "task-260319-234902",
      "step_name": "comparator",
      "chain_step": 2,
      "status": "completed",
      "cost": "0.23",
      "completed": "2026-03-19T23:51:51+05:00",
      "runner": "cc",
      "duration_sec": 169,
      "files_count": 0
    },
    "3-merge": {
      "task_id": "task-260319-235151",
      "step_name": "merge",
      "chain_step": 3,
      "status": "completed",
      "cost": "0.50",
      "completed": "2026-03-19T23:55:19+05:00",
      "runner": "cc",
      "duration_sec": 208,
      "files_count": 2
    }
  },
  "created": "2026-03-19T23:43:20+05:00",
  "step_names": [
    "cc-writer",
    "codex-writer",
    "comparator",
    "merge"
  ],
  "tg_msg_id": "300",
  "completed": "2026-03-19T23:55:19+05:00"
}